flask_openapi/__init__.py
flask_openapi/openapi.py
flask_openapi/core/__init__.py
flask_openapi/core/commands.py
flask_openapi/core/decorators.py
flask_openapi/core/marshmallow_apispec.py
flask_openapi/core/parser.py
flask_openapi/core/specs.py
flask_openapi/core/validation.py
flask_openapi/core/views.py
flask_openapi/ui/version_2/static/index.html
flask_openapi/ui/version_2/static/o2c.html
flask_openapi/ui/version_2/static/swagger-ui.js
flask_openapi/ui/version_2/static/swagger-ui.min.js
flask_openapi/ui/version_2/static/css/print.css
flask_openapi/ui/version_2/static/css/reset.css
flask_openapi/ui/version_2/static/css/screen.css
flask_openapi/ui/version_2/static/css/style.css
flask_openapi/ui/version_2/static/css/typography.css
flask_openapi/ui/version_2/static/fonts/DroidSans-Bold.ttf
flask_openapi/ui/version_2/static/fonts/DroidSans.ttf
flask_openapi/ui/version_2/static/fonts/droid-sans-v6-latin-700.eot
flask_openapi/ui/version_2/static/fonts/droid-sans-v6-latin-700.svg
flask_openapi/ui/version_2/static/fonts/droid-sans-v6-latin-700.ttf
flask_openapi/ui/version_2/static/fonts/droid-sans-v6-latin-700.woff
flask_openapi/ui/version_2/static/fonts/droid-sans-v6-latin-700.woff2
flask_openapi/ui/version_2/static/fonts/droid-sans-v6-latin-regular.eot
flask_openapi/ui/version_2/static/fonts/droid-sans-v6-latin-regular.svg
flask_openapi/ui/version_2/static/fonts/droid-sans-v6-latin-regular.ttf
flask_openapi/ui/version_2/static/fonts/droid-sans-v6-latin-regular.woff
flask_openapi/ui/version_2/static/fonts/droid-sans-v6-latin-regular.woff2
flask_openapi/ui/version_2/static/images/collapse.gif
flask_openapi/ui/version_2/static/images/expand.gif
flask_openapi/ui/version_2/static/images/explorer_icons.png
flask_openapi/ui/version_2/static/images/favicon-16x16.png
flask_openapi/ui/version_2/static/images/favicon-32x32.png
flask_openapi/ui/version_2/static/images/favicon.ico
flask_openapi/ui/version_2/static/images/logo_small.png
Flask_OpenAPI3_UI-9.10.9.dist-info/LICENSE
Flask_OpenAPI3_UI-9.10.9.dist-info/METADATA
Flask_OpenAPI3_UI-9.10.9.dist-info/WHEEL
Flask_OpenAPI3_UI-9.10.9.dist-info/entry_points.txt
Flask_OpenAPI3_UI-9.10.9.dist-info/top_level.txt
Flask_OpenAPI3_UI-9.10.9.dist-info/RECORD
