Metadata-Version: 2.1
Name: Flask-OpenAPI3-UI
Version: 9.10.9
Summary: Next generation OpenAPI v3 Integration for Flask based APIs. Based on Flasgger.
Author-email: Overflow Digital <team@overflow.digital>
Maintainer-email: Katerina Tiddy <katerina@overflow.digital>, Joshua Thompson-Lindley <joshua@overflow.digital>
License: The MIT License (MIT)
Project-URL: repository, https://github.com/overflowdigital/Flask-OpenAPI/
Keywords: flask,swagger,openapi,python,api,rest,openapi3
Classifier: Development Status :: 5 - Production/Stable
Classifier: Intended Audience :: Developers
Classifier: Programming Language :: Python :: 3
Classifier: Programming Language :: Python :: 3.8
Requires-Python: >=3.8.0
License-File: LICENSE
Requires-Dist: Flask >=2.1.2
Requires-Dist: PyYAML >=6.0
Requires-Dist: jsonschema >=4.17.0
Requires-Dist: mistune >=3.0.0
Requires-Dist: six >=1.16.0
